{
  "Projects": [
    {
      "title": "Project 1",
      "desc": [
        "Lorem ipsum dolor sit amet, consectetur adipiscing elit. Nulla euismod, nisl quis ultricies ultricies, nunc nisl ultricies elit, qu",
        "Lorem ipsum dolor sit amet, consectetur adipiscing elit. Nulla euismod, nisl quis ultricies ultricies, nunc nisl ultricies elit, qu"
      ],
      "year": "2015",
      "preview": "http://www.google.com",
      "code": "http://www.google.com",
      "images": [
        "/projects/lms.png",
        "/projects/lms.png",
        "/projects/lms.png"
      ],
      "tech": [
        "HTML",
        "CSS",
        "JavaScript"
      ],
      "slug": "project-1"
    }
  ]
}
